.gitignore
README.md
setup.py
tox.ini
examples/config.yml
examples/create_test_repository.sh
examples/execute_pipeline.sh
examples/setup.sh
examples/data/input.csv
git_history_profiler/__init__.py
git_history_profiler/main.py
git_history_profiler/utils.py
git_history_profiler.egg-info/PKG-INFO
git_history_profiler.egg-info/SOURCES.txt
git_history_profiler.egg-info/dependency_links.txt
git_history_profiler.egg-info/entry_points.txt
git_history_profiler.egg-info/requires.txt
git_history_profiler.egg-info/top_level.txt
git_history_profiler/tests/test_utils.py