Metadata-Version: 1.1
Name: git-history-profiler
Version: 0.0.2
Summary: Performance and stability profiling over commit historys.
Home-page: https://github.com/kpj/git_history_profiler
Author: kpj
Author-email: kpjkpjkpjkpjkpjkpj@gmail.com
License: MIT
Keywords: git profiling
Platform: UNKNOWN
Classifier: Development Status :: 3 - Alpha
Classifier: License :: OSI Approved :: MIT License
Classifier: Programming Language :: Python :: 3 :: Only
